py_simple_morse_code/CONSTANTS.py
py_simple_morse_code/__init__.py
py_simple_morse_code/__main__.py
py_simple_morse_code/py_simple_morse_code.py
py_simple_morse_code/signal_processing.py
py_simple_morse_code/version.py
py_simple_morse_code/__pycache__/CONSTANTS.cpython-311.pyc
py_simple_morse_code/__pycache__/__init__.cpython-311.pyc
py_simple_morse_code/__pycache__/gui.cpython-311.pyc
py_simple_morse_code/__pycache__/py_simple_morse_code.cpython-311.pyc
py_simple_morse_code/__pycache__/signal_processing.cpython-311.pyc
py_simple_morse_code/__pycache__/version.cpython-311.pyc
py_simple_morse_code_raspi-0.0.5.dist-info/LICENSE
py_simple_morse_code_raspi-0.0.5.dist-info/METADATA
py_simple_morse_code_raspi-0.0.5.dist-info/WHEEL
py_simple_morse_code_raspi-0.0.5.dist-info/top_level.txt
py_simple_morse_code_raspi-0.0.5.dist-info/RECORD
